gender_predictor/__init__.py
gender_predictor/gender_predictor.pkl
gender_predictor/predictor.py
gender_predictor_rp-0.3.1.dist-info/METADATA
gender_predictor_rp-0.3.1.dist-info/WHEEL
gender_predictor_rp-0.3.1.dist-info/top_level.txt
gender_predictor_rp-0.3.1.dist-info/RECORD
