Metadata-Version: 2.4
Name: gender_predictor_rp
Version: 0.3.1
Summary: Predict gender from Indian names using a trained ML model
Author: Rahul Patel
Author-email: your@email.com
Requires-Dist: scikit-learn
Requires-Dist: joblib
Dynamic: author
Dynamic: author-email
Dynamic: requires-dist
Dynamic: summary
